AutomatingInferenceLearningAndDesignUsingProbabilisticProgramming/README.md
AutomatingInferenceLearningAndDesignUsingProbabilisticProgramming/__init__.py
AutomatingInferenceLearningAndDesignUsingProbabilisticProgramming/__main__.py
AutomatingInferenceLearningAndDesignUsingProbabilisticProgramming/file.pdf
AutomatingInferenceLearningAndDesignUsingProbabilisticProgramming/index.html
automating_inference_learning_and_design_using_probabilistic_programming-2024.3.4.0.dist-info/METADATA
automating_inference_learning_and_design_using_probabilistic_programming-2024.3.4.0.dist-info/WHEEL
automating_inference_learning_and_design_using_probabilistic_programming-2024.3.4.0.dist-info/entry_points.txt
automating_inference_learning_and_design_using_probabilistic_programming-2024.3.4.0.dist-info/top_level.txt
automating_inference_learning_and_design_using_probabilistic_programming-2024.3.4.0.dist-info/RECORD
